neuralhedge/__init__.py
neuralhedge/data/__init__.py
neuralhedge/data/base.py
neuralhedge/data/market.py
neuralhedge/data/stochastic.py
neuralhedge/nn/__init__.py
neuralhedge/nn/base.py
neuralhedge/nn/blackschole.py
neuralhedge/nn/contigent.py
neuralhedge/nn/datahedger.py
neuralhedge/nn/datamanager.py
neuralhedge/nn/loss.py
neuralhedge/nn/network.py
neuralhedge/nn/trainer.py
neuralhedge/utils/__init__.py
neuralhedge/utils/evaluation.py
neuralhedge/utils/plotting.py
neuralhedge-0.1.0.dist-info/LICENSE
neuralhedge-0.1.0.dist-info/METADATA
neuralhedge-0.1.0.dist-info/WHEEL
neuralhedge-0.1.0.dist-info/top_level.txt
neuralhedge-0.1.0.dist-info/RECORD
