Metadata-Version: 2.1
Name: neuralhedge
Version: 0.1.0
Summary: Pytorch implementation of Deep Hedging, Utility Maximization and Portfolio Optimization
Author-email: Songyan Hou <justinhou95@gmail.com>
License: Apache License
Project-URL: Homepage, https://github.com/justinhou95/NeuralHedge
Keywords: feed,reader,tutorial
Classifier: Programming Language :: Python :: 3
Classifier: License :: OSI Approved :: Apache Software License
Classifier: Operating System :: OS Independent
Requires-Python: >=3.8
License-File: LICENSE
Requires-Dist: torch >=2.0
Requires-Dist: tqdm >=4.0
Requires-Dist: matplotlib >=3.0
Provides-Extra: dev
Requires-Dist: pytest ; extra == 'dev'
Requires-Dist: black ; extra == 'dev'
Requires-Dist: isort ; extra == 'dev'
Provides-Extra: exp
Requires-Dist: jupyter ; extra == 'exp'
Requires-Dist: notebook ; extra == 'exp'
Requires-Dist: seaborn ; extra == 'exp'
